README.md
setup.cfg
setup.py
bittrex/__init__.py
bittrex/bittrex.py
p3_bittrex.egg-info/PKG-INFO
p3_bittrex.egg-info/SOURCES.txt
p3_bittrex.egg-info/dependency_links.txt
p3_bittrex.egg-info/requires.txt
p3_bittrex.egg-info/top_level.txt
test/test_bittrex.py