Metadata-Version: 1.1
Name: p3-bittrex
Version: 0.1.6
Summary: Bittrex API pacakge
Home-page: https://github.com/bealox/p3-bittrex
Author: Andy Hsieh
Author-email: andy.hsieh@hotmail.com
License: LICENSE.txt
Platform: UNKNOWN
Classifier: Programming Language :: Python
Classifier: Programming Language :: Python :: 3
Classifier: Programming Language :: Python :: 3.6
Classifier: Environment :: Other Environment
Classifier: Intended Audience :: Developers
Classifier: License :: OSI Approved :: MIT License
Classifier: Operating System :: OS Independent
Classifier: Topic :: Office/Business :: Financial
